JSONGrapherRC/JSONRecordCreator.py
JSONGrapherRC/UnitPytesting.py
JSONGrapherRC/UnitpyCustomUnitsTesting.py
JSONGrapherRC/__init__.py
JSONGrapherRC/drag_and_drop_gui.py
JSONGrapherRC/units_list.py
jsongrapherrc-2.7.data/data/LICENSE
jsongrapherrc-2.7.data/data/README.md
jsongrapherrc-2.7.dist-info/LICENSE
jsongrapherrc-2.7.dist-info/METADATA
jsongrapherrc-2.7.dist-info/WHEEL
jsongrapherrc-2.7.dist-info/top_level.txt
jsongrapherrc-2.7.dist-info/RECORD
