Metadata-Version: 2.1
Name: jsongrapherrc
Version: 2.7
Summary: A python package for creating JSONGrapher Records.
Home-page: https://github.com/AdityaSavara/JSONGrapherRC
Author: Aditya Savara
Author-email: AditySavara2008@u.northwestern.edu
License: Unlicense
Classifier: License :: OSI Approved :: BSD License
Classifier: Programming Language :: Python
Classifier: Programming Language :: Python :: 3
Classifier: Programming Language :: Python :: 3.6
Classifier: Programming Language :: Python :: Implementation :: CPython
Classifier: Programming Language :: Python :: Implementation :: PyPy
Requires-Python: >=3.0.0
License-File: LICENSE
Requires-Dist: numpy
Provides-Extra: complete
Requires-Dist: matplotlib; extra == "complete"
Requires-Dist: plotly; extra == "complete"
Requires-Dist: unitpy; extra == "complete"
Requires-Dist: tkinterdnd2; extra == "complete"
